{
	"pattrstorage" : 	{
		"name" : "rfmpresets",
		"slots" : 		{
			"9" : 			{
				"id" : 9,
				"data" : 				{
					"grid[3]::umenu" : [ 0 ],
					"midi[3]::kslider" : [ 0, 127, 3, 127, 5, 127, 7, 127, 10, 127 ],
					"midi[3]::number" : [ 4 ],
					"midi[3]::number[1]" : [ 16 ],
					"midi[3]::umenu" : [ 5 ],
					"midi[3]::notes[15]::number" : [ 60 ],
					"midi[3]::notes[15]::toggle" : [ 1 ],
					"midi[3]::notes[14]::number" : [ 60 ],
					"midi[3]::notes[14]::toggle" : [ 1 ],
					"midi[3]::notes[13]::number" : [ 60 ],
					"midi[3]::notes[13]::toggle" : [ 1 ],
					"midi[3]::notes[12]::number" : [ 60 ],
					"midi[3]::notes[12]::toggle" : [ 1 ],
					"midi[3]::notes[11]::number" : [ 60 ],
					"midi[3]::notes[11]::toggle" : [ 1 ],
					"midi[3]::notes[10]::number" : [ 60 ],
					"midi[3]::notes[10]::toggle" : [ 1 ],
					"midi[3]::notes[9]::number" : [ 60 ],
					"midi[3]::notes[9]::toggle" : [ 1 ],
					"midi[3]::notes[8]::number" : [ 60 ],
					"midi[3]::notes[8]::toggle" : [ 1 ],
					"midi[3]::notes[7]::number" : [ 60 ],
					"midi[3]::notes[7]::toggle" : [ 1 ],
					"midi[3]::notes[6]::number" : [ 60 ],
					"midi[3]::notes[6]::toggle" : [ 1 ],
					"midi[3]::notes[5]::number" : [ 60 ],
					"midi[3]::notes[5]::toggle" : [ 1 ],
					"midi[3]::notes[4]::number" : [ 60 ],
					"midi[3]::notes[4]::toggle" : [ 1 ],
					"midi[3]::notes[3]::number" : [ 60 ],
					"midi[3]::notes[3]::toggle" : [ 1 ],
					"midi[3]::notes[2]::number" : [ 60 ],
					"midi[3]::notes[2]::toggle" : [ 1 ],
					"midi[3]::notes[1]::number" : [ 60 ],
					"midi[3]::notes[1]::toggle" : [ 1 ],
					"midi[3]::notes::number" : [ 60 ],
					"midi[3]::notes::toggle" : [ 1 ],
					"midi[3]::stepgroup::stepsel[15]::number" : [ 0 ],
					"midi[3]::stepgroup::stepsel[15]::toggle" : [ 0 ],
					"midi[3]::stepgroup::stepsel[14]::number" : [ 0 ],
					"midi[3]::stepgroup::stepsel[14]::toggle" : [ 0 ],
					"midi[3]::stepgroup::stepsel[13]::number" : [ 0 ],
					"midi[3]::stepgroup::stepsel[13]::toggle" : [ 0 ],
					"midi[3]::stepgroup::stepsel[12]::number" : [ 0 ],
					"midi[3]::stepgroup::stepsel[12]::toggle" : [ 0 ],
					"midi[3]::stepgroup::stepsel[11]::number" : [ 0 ],
					"midi[3]::stepgroup::stepsel[11]::toggle" : [ 0 ],
					"midi[3]::stepgroup::stepsel[10]::number" : [ 0 ],
					"midi[3]::stepgroup::stepsel[10]::toggle" : [ 0 ],
					"midi[3]::stepgroup::stepsel[9]::number" : [ 0 ],
					"midi[3]::stepgroup::stepsel[9]::toggle" : [ 0 ],
					"midi[3]::stepgroup::stepsel[8]::number" : [ 0 ],
					"midi[3]::stepgroup::stepsel[8]::toggle" : [ 0 ],
					"midi[3]::stepgroup::stepsel[7]::number" : [ 0 ],
					"midi[3]::stepgroup::stepsel[7]::toggle" : [ 0 ],
					"midi[3]::stepgroup::stepsel[6]::number" : [ 0 ],
					"midi[3]::stepgroup::stepsel[6]::toggle" : [ 0 ],
					"midi[3]::stepgroup::stepsel[5]::number" : [ 0 ],
					"midi[3]::stepgroup::stepsel[5]::toggle" : [ 0 ],
					"midi[3]::stepgroup::stepsel[4]::number" : [ 0 ],
					"midi[3]::stepgroup::stepsel[4]::toggle" : [ 0 ],
					"midi[3]::stepgroup::stepsel[3]::number" : [ 0 ],
					"midi[3]::stepgroup::stepsel[3]::toggle" : [ 0 ],
					"midi[3]::stepgroup::stepsel[2]::number" : [ 0 ],
					"midi[3]::stepgroup::stepsel[2]::toggle" : [ 0 ],
					"midi[3]::stepgroup::stepsel[1]::number" : [ 0 ],
					"midi[3]::stepgroup::stepsel[1]::toggle" : [ 0 ],
					"midi[3]::stepgroup::stepsel::number" : [ 0 ],
					"midi[3]::stepgroup::stepsel::toggle" : [ 0 ],
					"jr.noteouted::number" : [ 1 ],
					"jr.noteouted::number[1]" : [ 100 ],
					"jr.noteouted::number[2]" : [ 500 ],
					"jr.noteouted::number[3]" : [ 118 ],
					"jr.noteouted::number[4]" : [ 103 ],
					"jr.noteouted::number[5]" : [ 127 ],
					"jr.noteouted::number[6]" : [ 0 ],
					"jr.noteouted::number[7]" : [ 0 ],
					"jr.noteouted::number[8]" : [ 1760 ],
					"jr.noteouted::number[9]" : [ 2000 ],
					"jr.noteouted::toggle" : [ 1 ],
					"jr.noteouted::toggle[1]" : [ 0 ],
					"jr.noteouted::toggle[2]" : [ 1 ],
					"jr.noteouted::toggle[3]" : [ 1 ],
					"grid[2]::umenu" : [ 0 ],
					"midi[2]::kslider" : [ 0, 127, 3, 127, 7, 127, 10, 127 ],
					"midi[2]::number" : [ 3 ],
					"midi[2]::number[1]" : [ 16 ],
					"midi[2]::umenu" : [ 5 ],
					"midi[2]::notes[15]::number" : [ 60 ],
					"midi[2]::notes[15]::toggle" : [ 1 ],
					"midi[2]::notes[14]::number" : [ 60 ],
					"midi[2]::notes[14]::toggle" : [ 1 ],
					"midi[2]::notes[13]::number" : [ 60 ],
					"midi[2]::notes[13]::toggle" : [ 1 ],
					"midi[2]::notes[12]::number" : [ 60 ],
					"midi[2]::notes[12]::toggle" : [ 1 ],
					"midi[2]::notes[11]::number" : [ 60 ],
					"midi[2]::notes[11]::toggle" : [ 1 ],
					"midi[2]::notes[10]::number" : [ 60 ],
					"midi[2]::notes[10]::toggle" : [ 1 ],
					"midi[2]::notes[9]::number" : [ 60 ],
					"midi[2]::notes[9]::toggle" : [ 1 ],
					"midi[2]::notes[8]::number" : [ 60 ],
					"midi[2]::notes[8]::toggle" : [ 1 ],
					"midi[2]::notes[7]::number" : [ 60 ],
					"midi[2]::notes[7]::toggle" : [ 1 ],
					"midi[2]::notes[6]::number" : [ 60 ],
					"midi[2]::notes[6]::toggle" : [ 1 ],
					"midi[2]::notes[5]::number" : [ 60 ],
					"midi[2]::notes[5]::toggle" : [ 1 ],
					"midi[2]::notes[4]::number" : [ 60 ],
					"midi[2]::notes[4]::toggle" : [ 1 ],
					"midi[2]::notes[3]::number" : [ 60 ],
					"midi[2]::notes[3]::toggle" : [ 1 ],
					"midi[2]::notes[2]::number" : [ 60 ],
					"midi[2]::notes[2]::toggle" : [ 1 ],
					"midi[2]::notes[1]::number" : [ 60 ],
					"midi[2]::notes[1]::toggle" : [ 1 ],
					"midi[2]::notes::number" : [ 60 ],
					"midi[2]::notes::toggle" : [ 1 ],
					"midi[2]::stepgroup::stepsel[15]::number" : [ 0 ],
					"midi[2]::stepgroup::stepsel[15]::toggle" : [ 0 ],
					"midi[2]::stepgroup::stepsel[14]::number" : [ 0 ],
					"midi[2]::stepgroup::stepsel[14]::toggle" : [ 0 ],
					"midi[2]::stepgroup::stepsel[13]::number" : [ 0 ],
					"midi[2]::stepgroup::stepsel[13]::toggle" : [ 0 ],
					"midi[2]::stepgroup::stepsel[12]::number" : [ 0 ],
					"midi[2]::stepgroup::stepsel[12]::toggle" : [ 0 ],
					"midi[2]::stepgroup::stepsel[11]::number" : [ 0 ],
					"midi[2]::stepgroup::stepsel[11]::toggle" : [ 0 ],
					"midi[2]::stepgroup::stepsel[10]::number" : [ 0 ],
					"midi[2]::stepgroup::stepsel[10]::toggle" : [ 0 ],
					"midi[2]::stepgroup::stepsel[9]::number" : [ 0 ],
					"midi[2]::stepgroup::stepsel[9]::toggle" : [ 0 ],
					"midi[2]::stepgroup::stepsel[8]::number" : [ 0 ],
					"midi[2]::stepgroup::stepsel[8]::toggle" : [ 0 ],
					"midi[2]::stepgroup::stepsel[7]::number" : [ 0 ],
					"midi[2]::stepgroup::stepsel[7]::toggle" : [ 0 ],
					"midi[2]::stepgroup::stepsel[6]::number" : [ 0 ],
					"midi[2]::stepgroup::stepsel[6]::toggle" : [ 0 ],
					"midi[2]::stepgroup::stepsel[5]::number" : [ 0 ],
					"midi[2]::stepgroup::stepsel[5]::toggle" : [ 0 ],
					"midi[2]::stepgroup::stepsel[4]::number" : [ 0 ],
					"midi[2]::stepgroup::stepsel[4]::toggle" : [ 0 ],
					"midi[2]::stepgroup::stepsel[3]::number" : [ 0 ],
					"midi[2]::stepgroup::stepsel[3]::toggle" : [ 0 ],
					"midi[2]::stepgroup::stepsel[2]::number" : [ 0 ],
					"midi[2]::stepgroup::stepsel[2]::toggle" : [ 0 ],
					"midi[2]::stepgroup::stepsel[1]::number" : [ 0 ],
					"midi[2]::stepgroup::stepsel[1]::toggle" : [ 0 ],
					"midi[2]::stepgroup::stepsel::number" : [ 0 ],
					"midi[2]::stepgroup::stepsel::toggle" : [ 0 ],
					"jr.noteouted[1]::number" : [ 2 ],
					"jr.noteouted[1]::number[1]" : [ 100 ],
					"jr.noteouted[1]::number[2]" : [ 500 ],
					"jr.noteouted[1]::number[3]" : [ 127 ],
					"jr.noteouted[1]::number[4]" : [ 0 ],
					"jr.noteouted[1]::number[5]" : [ 127 ],
					"jr.noteouted[1]::number[6]" : [ 0 ],
					"jr.noteouted[1]::number[7]" : [ 0 ],
					"jr.noteouted[1]::number[8]" : [ 10 ],
					"jr.noteouted[1]::number[9]" : [ 2000 ],
					"jr.noteouted[1]::toggle" : [ 0 ],
					"jr.noteouted[1]::toggle[1]" : [ 0 ],
					"jr.noteouted[1]::toggle[2]" : [ 1 ],
					"jr.noteouted[1]::toggle[3]" : [ 0 ],
					"grid[1]::umenu" : [ 1 ],
					"midi[1]::kslider" : [ 0, 127, 3, 127, 5, 127, 10, 127 ],
					"midi[1]::number" : [ 3 ],
					"midi[1]::number[1]" : [ 16 ],
					"midi[1]::umenu" : [ 5 ],
					"midi[1]::notes[15]::number" : [ 60 ],
					"midi[1]::notes[15]::toggle" : [ 1 ],
					"midi[1]::notes[14]::number" : [ 67 ],
					"midi[1]::notes[14]::toggle" : [ 1 ],
					"midi[1]::notes[13]::number" : [ 63 ],
					"midi[1]::notes[13]::toggle" : [ 1 ],
					"midi[1]::notes[12]::number" : [ 60 ],
					"midi[1]::notes[12]::toggle" : [ 1 ],
					"midi[1]::notes[11]::number" : [ 63 ],
					"midi[1]::notes[11]::toggle" : [ 0 ],
					"midi[1]::notes[10]::number" : [ 67 ],
					"midi[1]::notes[10]::toggle" : [ 1 ],
					"midi[1]::notes[9]::number" : [ 62 ],
					"midi[1]::notes[9]::toggle" : [ 0 ],
					"midi[1]::notes[8]::number" : [ 60 ],
					"midi[1]::notes[8]::toggle" : [ 1 ],
					"midi[1]::notes[7]::number" : [ 67 ],
					"midi[1]::notes[7]::toggle" : [ 1 ],
					"midi[1]::notes[6]::number" : [ 60 ],
					"midi[1]::notes[6]::toggle" : [ 1 ],
					"midi[1]::notes[5]::number" : [ 63 ],
					"midi[1]::notes[5]::toggle" : [ 0 ],
					"midi[1]::notes[4]::number" : [ 67 ],
					"midi[1]::notes[4]::toggle" : [ 1 ],
					"midi[1]::notes[3]::number" : [ 60 ],
					"midi[1]::notes[3]::toggle" : [ 0 ],
					"midi[1]::notes[2]::number" : [ 60 ],
					"midi[1]::notes[2]::toggle" : [ 1 ],
					"midi[1]::notes[1]::number" : [ 62 ],
					"midi[1]::notes[1]::toggle" : [ 1 ],
					"midi[1]::notes::number" : [ 60 ],
					"midi[1]::notes::toggle" : [ 1 ],
					"midi[1]::stepgroup::stepsel[15]::number" : [ 0 ],
					"midi[1]::stepgroup::stepsel[15]::toggle" : [ 0 ],
					"midi[1]::stepgroup::stepsel[14]::number" : [ 4 ],
					"midi[1]::stepgroup::stepsel[14]::toggle" : [ 0 ],
					"midi[1]::stepgroup::stepsel[13]::number" : [ 1 ],
					"midi[1]::stepgroup::stepsel[13]::toggle" : [ 1 ],
					"midi[1]::stepgroup::stepsel[12]::number" : [ 0 ],
					"midi[1]::stepgroup::stepsel[12]::toggle" : [ 0 ],
					"midi[1]::stepgroup::stepsel[11]::number" : [ 1 ],
					"midi[1]::stepgroup::stepsel[11]::toggle" : [ 1 ],
					"midi[1]::stepgroup::stepsel[10]::number" : [ 4 ],
					"midi[1]::stepgroup::stepsel[10]::toggle" : [ 0 ],
					"midi[1]::stepgroup::stepsel[9]::number" : [ 1 ],
					"midi[1]::stepgroup::stepsel[9]::toggle" : [ 0 ],
					"midi[1]::stepgroup::stepsel[8]::number" : [ 0 ],
					"midi[1]::stepgroup::stepsel[8]::toggle" : [ 0 ],
					"midi[1]::stepgroup::stepsel[7]::number" : [ 4 ],
					"midi[1]::stepgroup::stepsel[7]::toggle" : [ 0 ],
					"midi[1]::stepgroup::stepsel[6]::number" : [ 0 ],
					"midi[1]::stepgroup::stepsel[6]::toggle" : [ 0 ],
					"midi[1]::stepgroup::stepsel[5]::number" : [ 1 ],
					"midi[1]::stepgroup::stepsel[5]::toggle" : [ 1 ],
					"midi[1]::stepgroup::stepsel[4]::number" : [ 4 ],
					"midi[1]::stepgroup::stepsel[4]::toggle" : [ 0 ],
					"midi[1]::stepgroup::stepsel[3]::number" : [ 0 ],
					"midi[1]::stepgroup::stepsel[3]::toggle" : [ 0 ],
					"midi[1]::stepgroup::stepsel[2]::number" : [ 0 ],
					"midi[1]::stepgroup::stepsel[2]::toggle" : [ 0 ],
					"midi[1]::stepgroup::stepsel[1]::number" : [ 1 ],
					"midi[1]::stepgroup::stepsel[1]::toggle" : [ 0 ],
					"midi[1]::stepgroup::stepsel::number" : [ 0 ],
					"midi[1]::stepgroup::stepsel::toggle" : [ 0 ],
					"jr.noteouted[2]::number" : [ 3 ],
					"jr.noteouted[2]::number[1]" : [ 100 ],
					"jr.noteouted[2]::number[2]" : [ 500 ],
					"jr.noteouted[2]::number[3]" : [ 117 ],
					"jr.noteouted[2]::number[4]" : [ 69 ],
					"jr.noteouted[2]::number[5]" : [ 127 ],
					"jr.noteouted[2]::number[6]" : [ 0 ],
					"jr.noteouted[2]::number[7]" : [ 0 ],
					"jr.noteouted[2]::number[8]" : [ 914 ],
					"jr.noteouted[2]::number[9]" : [ 2000 ],
					"jr.noteouted[2]::toggle" : [ 1 ],
					"jr.noteouted[2]::toggle[1]" : [ 0 ],
					"jr.noteouted[2]::toggle[2]" : [ 1 ],
					"jr.noteouted[2]::toggle[3]" : [ 1 ],
					"grid::umenu" : [ 1 ],
					"midi::kslider" : [ -1 ],
					"midi::number" : [ 1 ],
					"midi::number[1]" : [ 10 ],
					"midi::umenu" : [ 3 ],
					"midi::notes[15]::number" : [ 36 ],
					"midi::notes[15]::toggle" : [ 1 ],
					"midi::notes[14]::number" : [ 43 ],
					"midi::notes[14]::toggle" : [ 1 ],
					"midi::notes[13]::number" : [ 36 ],
					"midi::notes[13]::toggle" : [ 1 ],
					"midi::notes[12]::number" : [ 43 ],
					"midi::notes[12]::toggle" : [ 1 ],
					"midi::notes[11]::number" : [ 43 ],
					"midi::notes[11]::toggle" : [ 1 ],
					"midi::notes[10]::number" : [ 38 ],
					"midi::notes[10]::toggle" : [ 1 ],
					"midi::notes[9]::number" : [ 36 ],
					"midi::notes[9]::toggle" : [ 1 ],
					"midi::notes[8]::number" : [ 43 ],
					"midi::notes[8]::toggle" : [ 1 ],
					"midi::notes[7]::number" : [ 38 ],
					"midi::notes[7]::toggle" : [ 1 ],
					"midi::notes[6]::number" : [ 36 ],
					"midi::notes[6]::toggle" : [ 1 ],
					"midi::notes[5]::number" : [ 43 ],
					"midi::notes[5]::toggle" : [ 1 ],
					"midi::notes[4]::number" : [ 38 ],
					"midi::notes[4]::toggle" : [ 1 ],
					"midi::notes[3]::number" : [ 36 ],
					"midi::notes[3]::toggle" : [ 1 ],
					"midi::notes[2]::number" : [ 43 ],
					"midi::notes[2]::toggle" : [ 1 ],
					"midi::notes[1]::number" : [ 38 ],
					"midi::notes[1]::toggle" : [ 1 ],
					"midi::notes::number" : [ 43 ],
					"midi::notes::toggle" : [ 1 ],
					"midi::stepgroup::stepsel[15]::number" : [ 0 ],
					"midi::stepgroup::stepsel[15]::toggle" : [ 0 ],
					"midi::stepgroup::stepsel[14]::number" : [ 4 ],
					"midi::stepgroup::stepsel[14]::toggle" : [ 0 ],
					"midi::stepgroup::stepsel[13]::number" : [ 0 ],
					"midi::stepgroup::stepsel[13]::toggle" : [ 0 ],
					"midi::stepgroup::stepsel[12]::number" : [ 4 ],
					"midi::stepgroup::stepsel[12]::toggle" : [ 0 ],
					"midi::stepgroup::stepsel[11]::number" : [ 4 ],
					"midi::stepgroup::stepsel[11]::toggle" : [ 0 ],
					"midi::stepgroup::stepsel[10]::number" : [ 1 ],
					"midi::stepgroup::stepsel[10]::toggle" : [ 0 ],
					"midi::stepgroup::stepsel[9]::number" : [ 0 ],
					"midi::stepgroup::stepsel[9]::toggle" : [ 0 ],
					"midi::stepgroup::stepsel[8]::number" : [ 4 ],
					"midi::stepgroup::stepsel[8]::toggle" : [ 0 ],
					"midi::stepgroup::stepsel[7]::number" : [ 1 ],
					"midi::stepgroup::stepsel[7]::toggle" : [ 0 ],
					"midi::stepgroup::stepsel[6]::number" : [ 0 ],
					"midi::stepgroup::stepsel[6]::toggle" : [ 0 ],
					"midi::stepgroup::stepsel[5]::number" : [ 4 ],
					"midi::stepgroup::stepsel[5]::toggle" : [ 0 ],
					"midi::stepgroup::stepsel[4]::number" : [ 1 ],
					"midi::stepgroup::stepsel[4]::toggle" : [ 0 ],
					"midi::stepgroup::stepsel[3]::number" : [ 0 ],
					"midi::stepgroup::stepsel[3]::toggle" : [ 0 ],
					"midi::stepgroup::stepsel[2]::number" : [ 4 ],
					"midi::stepgroup::stepsel[2]::toggle" : [ 0 ],
					"midi::stepgroup::stepsel[1]::number" : [ 1 ],
					"midi::stepgroup::stepsel[1]::toggle" : [ 0 ],
					"midi::stepgroup::stepsel::number" : [ 4 ],
					"midi::stepgroup::stepsel::toggle" : [ 0 ],
					"jr.noteouted[3]::number" : [ 4 ],
					"jr.noteouted[3]::number[1]" : [ 100 ],
					"jr.noteouted[3]::number[2]" : [ 500 ],
					"jr.noteouted[3]::number[3]" : [ 127 ],
					"jr.noteouted[3]::number[4]" : [ 0 ],
					"jr.noteouted[3]::number[5]" : [ 127 ],
					"jr.noteouted[3]::number[6]" : [ 0 ],
					"jr.noteouted[3]::number[7]" : [ 0 ],
					"jr.noteouted[3]::number[8]" : [ 10 ],
					"jr.noteouted[3]::number[9]" : [ 2000 ],
					"jr.noteouted[3]::toggle" : [ 0 ],
					"jr.noteouted[3]::toggle[1]" : [ 0 ],
					"jr.noteouted[3]::toggle[2]" : [ 1 ],
					"jr.noteouted[3]::toggle[3]" : [ 0 ]
				}

			}
,
			"16" : 			{
				"id" : 16,
				"data" : 				{
					"grid[3]::umenu" : [ 0 ],
					"midi[3]::kslider" : [ -1 ],
					"midi[3]::number" : [ 3 ],
					"midi[3]::number[1]" : [ 16 ],
					"midi[3]::umenu" : [ 5 ],
					"midi[3]::notes[15]::number" : [ 60 ],
					"midi[3]::notes[15]::toggle" : [ 1 ],
					"midi[3]::notes[14]::number" : [ 60 ],
					"midi[3]::notes[14]::toggle" : [ 1 ],
					"midi[3]::notes[13]::number" : [ 60 ],
					"midi[3]::notes[13]::toggle" : [ 1 ],
					"midi[3]::notes[12]::number" : [ 60 ],
					"midi[3]::notes[12]::toggle" : [ 1 ],
					"midi[3]::notes[11]::number" : [ 60 ],
					"midi[3]::notes[11]::toggle" : [ 1 ],
					"midi[3]::notes[10]::number" : [ 60 ],
					"midi[3]::notes[10]::toggle" : [ 1 ],
					"midi[3]::notes[9]::number" : [ 60 ],
					"midi[3]::notes[9]::toggle" : [ 1 ],
					"midi[3]::notes[8]::number" : [ 60 ],
					"midi[3]::notes[8]::toggle" : [ 1 ],
					"midi[3]::notes[7]::number" : [ 60 ],
					"midi[3]::notes[7]::toggle" : [ 1 ],
					"midi[3]::notes[6]::number" : [ 60 ],
					"midi[3]::notes[6]::toggle" : [ 1 ],
					"midi[3]::notes[5]::number" : [ 60 ],
					"midi[3]::notes[5]::toggle" : [ 1 ],
					"midi[3]::notes[4]::number" : [ 60 ],
					"midi[3]::notes[4]::toggle" : [ 1 ],
					"midi[3]::notes[3]::number" : [ 60 ],
					"midi[3]::notes[3]::toggle" : [ 1 ],
					"midi[3]::notes[2]::number" : [ 60 ],
					"midi[3]::notes[2]::toggle" : [ 1 ],
					"midi[3]::notes[1]::number" : [ 60 ],
					"midi[3]::notes[1]::toggle" : [ 1 ],
					"midi[3]::notes::number" : [ 60 ],
					"midi[3]::notes::toggle" : [ 1 ],
					"midi[3]::stepgroup::stepsel[15]::number" : [ 0 ],
					"midi[3]::stepgroup::stepsel[15]::toggle" : [ 0 ],
					"midi[3]::stepgroup::stepsel[14]::number" : [ 0 ],
					"midi[3]::stepgroup::stepsel[14]::toggle" : [ 0 ],
					"midi[3]::stepgroup::stepsel[13]::number" : [ 0 ],
					"midi[3]::stepgroup::stepsel[13]::toggle" : [ 0 ],
					"midi[3]::stepgroup::stepsel[12]::number" : [ 0 ],
					"midi[3]::stepgroup::stepsel[12]::toggle" : [ 0 ],
					"midi[3]::stepgroup::stepsel[11]::number" : [ 0 ],
					"midi[3]::stepgroup::stepsel[11]::toggle" : [ 0 ],
					"midi[3]::stepgroup::stepsel[10]::number" : [ 0 ],
					"midi[3]::stepgroup::stepsel[10]::toggle" : [ 0 ],
					"midi[3]::stepgroup::stepsel[9]::number" : [ 0 ],
					"midi[3]::stepgroup::stepsel[9]::toggle" : [ 0 ],
					"midi[3]::stepgroup::stepsel[8]::number" : [ 0 ],
					"midi[3]::stepgroup::stepsel[8]::toggle" : [ 0 ],
					"midi[3]::stepgroup::stepsel[7]::number" : [ 0 ],
					"midi[3]::stepgroup::stepsel[7]::toggle" : [ 0 ],
					"midi[3]::stepgroup::stepsel[6]::number" : [ 0 ],
					"midi[3]::stepgroup::stepsel[6]::toggle" : [ 0 ],
					"midi[3]::stepgroup::stepsel[5]::number" : [ 0 ],
					"midi[3]::stepgroup::stepsel[5]::toggle" : [ 0 ],
					"midi[3]::stepgroup::stepsel[4]::number" : [ 0 ],
					"midi[3]::stepgroup::stepsel[4]::toggle" : [ 0 ],
					"midi[3]::stepgroup::stepsel[3]::number" : [ 0 ],
					"midi[3]::stepgroup::stepsel[3]::toggle" : [ 0 ],
					"midi[3]::stepgroup::stepsel[2]::number" : [ 0 ],
					"midi[3]::stepgroup::stepsel[2]::toggle" : [ 0 ],
					"midi[3]::stepgroup::stepsel[1]::number" : [ 0 ],
					"midi[3]::stepgroup::stepsel[1]::toggle" : [ 0 ],
					"midi[3]::stepgroup::stepsel::number" : [ 0 ],
					"midi[3]::stepgroup::stepsel::toggle" : [ 0 ],
					"jr.noteouted::number" : [ 1 ],
					"jr.noteouted::number[1]" : [ 100 ],
					"jr.noteouted::number[2]" : [ 500 ],
					"jr.noteouted::number[3]" : [ 127 ],
					"jr.noteouted::number[4]" : [ 0 ],
					"jr.noteouted::number[5]" : [ 127 ],
					"jr.noteouted::number[6]" : [ 0 ],
					"jr.noteouted::number[7]" : [ 0 ],
					"jr.noteouted::number[8]" : [ 10 ],
					"jr.noteouted::number[9]" : [ 2000 ],
					"jr.noteouted::toggle" : [ 0 ],
					"jr.noteouted::toggle[1]" : [ 0 ],
					"jr.noteouted::toggle[2]" : [ 1 ],
					"jr.noteouted::toggle[3]" : [ 0 ],
					"grid[2]::umenu" : [ 0 ],
					"midi[2]::kslider" : [ -1 ],
					"midi[2]::number" : [ 3 ],
					"midi[2]::number[1]" : [ 16 ],
					"midi[2]::umenu" : [ 5 ],
					"midi[2]::notes[15]::number" : [ 60 ],
					"midi[2]::notes[15]::toggle" : [ 1 ],
					"midi[2]::notes[14]::number" : [ 60 ],
					"midi[2]::notes[14]::toggle" : [ 1 ],
					"midi[2]::notes[13]::number" : [ 60 ],
					"midi[2]::notes[13]::toggle" : [ 1 ],
					"midi[2]::notes[12]::number" : [ 60 ],
					"midi[2]::notes[12]::toggle" : [ 1 ],
					"midi[2]::notes[11]::number" : [ 60 ],
					"midi[2]::notes[11]::toggle" : [ 1 ],
					"midi[2]::notes[10]::number" : [ 60 ],
					"midi[2]::notes[10]::toggle" : [ 1 ],
					"midi[2]::notes[9]::number" : [ 60 ],
					"midi[2]::notes[9]::toggle" : [ 1 ],
					"midi[2]::notes[8]::number" : [ 60 ],
					"midi[2]::notes[8]::toggle" : [ 1 ],
					"midi[2]::notes[7]::number" : [ 60 ],
					"midi[2]::notes[7]::toggle" : [ 1 ],
					"midi[2]::notes[6]::number" : [ 60 ],
					"midi[2]::notes[6]::toggle" : [ 1 ],
					"midi[2]::notes[5]::number" : [ 60 ],
					"midi[2]::notes[5]::toggle" : [ 1 ],
					"midi[2]::notes[4]::number" : [ 60 ],
					"midi[2]::notes[4]::toggle" : [ 1 ],
					"midi[2]::notes[3]::number" : [ 60 ],
					"midi[2]::notes[3]::toggle" : [ 1 ],
					"midi[2]::notes[2]::number" : [ 60 ],
					"midi[2]::notes[2]::toggle" : [ 1 ],
					"midi[2]::notes[1]::number" : [ 60 ],
					"midi[2]::notes[1]::toggle" : [ 1 ],
					"midi[2]::notes::number" : [ 60 ],
					"midi[2]::notes::toggle" : [ 1 ],
					"midi[2]::stepgroup::stepsel[15]::number" : [ 0 ],
					"midi[2]::stepgroup::stepsel[15]::toggle" : [ 0 ],
					"midi[2]::stepgroup::stepsel[14]::number" : [ 0 ],
					"midi[2]::stepgroup::stepsel[14]::toggle" : [ 0 ],
					"midi[2]::stepgroup::stepsel[13]::number" : [ 0 ],
					"midi[2]::stepgroup::stepsel[13]::toggle" : [ 0 ],
					"midi[2]::stepgroup::stepsel[12]::number" : [ 0 ],
					"midi[2]::stepgroup::stepsel[12]::toggle" : [ 0 ],
					"midi[2]::stepgroup::stepsel[11]::number" : [ 0 ],
					"midi[2]::stepgroup::stepsel[11]::toggle" : [ 0 ],
					"midi[2]::stepgroup::stepsel[10]::number" : [ 0 ],
					"midi[2]::stepgroup::stepsel[10]::toggle" : [ 0 ],
					"midi[2]::stepgroup::stepsel[9]::number" : [ 0 ],
					"midi[2]::stepgroup::stepsel[9]::toggle" : [ 0 ],
					"midi[2]::stepgroup::stepsel[8]::number" : [ 0 ],
					"midi[2]::stepgroup::stepsel[8]::toggle" : [ 0 ],
					"midi[2]::stepgroup::stepsel[7]::number" : [ 0 ],
					"midi[2]::stepgroup::stepsel[7]::toggle" : [ 0 ],
					"midi[2]::stepgroup::stepsel[6]::number" : [ 0 ],
					"midi[2]::stepgroup::stepsel[6]::toggle" : [ 0 ],
					"midi[2]::stepgroup::stepsel[5]::number" : [ 0 ],
					"midi[2]::stepgroup::stepsel[5]::toggle" : [ 0 ],
					"midi[2]::stepgroup::stepsel[4]::number" : [ 0 ],
					"midi[2]::stepgroup::stepsel[4]::toggle" : [ 0 ],
					"midi[2]::stepgroup::stepsel[3]::number" : [ 0 ],
					"midi[2]::stepgroup::stepsel[3]::toggle" : [ 0 ],
					"midi[2]::stepgroup::stepsel[2]::number" : [ 0 ],
					"midi[2]::stepgroup::stepsel[2]::toggle" : [ 0 ],
					"midi[2]::stepgroup::stepsel[1]::number" : [ 0 ],
					"midi[2]::stepgroup::stepsel[1]::toggle" : [ 0 ],
					"midi[2]::stepgroup::stepsel::number" : [ 0 ],
					"midi[2]::stepgroup::stepsel::toggle" : [ 0 ],
					"jr.noteouted[1]::number" : [ 1 ],
					"jr.noteouted[1]::number[1]" : [ 100 ],
					"jr.noteouted[1]::number[2]" : [ 500 ],
					"jr.noteouted[1]::number[3]" : [ 127 ],
					"jr.noteouted[1]::number[4]" : [ 0 ],
					"jr.noteouted[1]::number[5]" : [ 127 ],
					"jr.noteouted[1]::number[6]" : [ 0 ],
					"jr.noteouted[1]::number[7]" : [ 0 ],
					"jr.noteouted[1]::number[8]" : [ 10 ],
					"jr.noteouted[1]::number[9]" : [ 2000 ],
					"jr.noteouted[1]::toggle" : [ 0 ],
					"jr.noteouted[1]::toggle[1]" : [ 0 ],
					"jr.noteouted[1]::toggle[2]" : [ 1 ],
					"jr.noteouted[1]::toggle[3]" : [ 0 ],
					"grid[1]::umenu" : [ 0 ],
					"midi[1]::kslider" : [ -1 ],
					"midi[1]::number" : [ 3 ],
					"midi[1]::number[1]" : [ 16 ],
					"midi[1]::umenu" : [ 5 ],
					"midi[1]::notes[15]::number" : [ 60 ],
					"midi[1]::notes[15]::toggle" : [ 1 ],
					"midi[1]::notes[14]::number" : [ 60 ],
					"midi[1]::notes[14]::toggle" : [ 1 ],
					"midi[1]::notes[13]::number" : [ 60 ],
					"midi[1]::notes[13]::toggle" : [ 1 ],
					"midi[1]::notes[12]::number" : [ 60 ],
					"midi[1]::notes[12]::toggle" : [ 1 ],
					"midi[1]::notes[11]::number" : [ 60 ],
					"midi[1]::notes[11]::toggle" : [ 1 ],
					"midi[1]::notes[10]::number" : [ 60 ],
					"midi[1]::notes[10]::toggle" : [ 1 ],
					"midi[1]::notes[9]::number" : [ 60 ],
					"midi[1]::notes[9]::toggle" : [ 1 ],
					"midi[1]::notes[8]::number" : [ 60 ],
					"midi[1]::notes[8]::toggle" : [ 1 ],
					"midi[1]::notes[7]::number" : [ 60 ],
					"midi[1]::notes[7]::toggle" : [ 1 ],
					"midi[1]::notes[6]::number" : [ 60 ],
					"midi[1]::notes[6]::toggle" : [ 1 ],
					"midi[1]::notes[5]::number" : [ 60 ],
					"midi[1]::notes[5]::toggle" : [ 1 ],
					"midi[1]::notes[4]::number" : [ 60 ],
					"midi[1]::notes[4]::toggle" : [ 1 ],
					"midi[1]::notes[3]::number" : [ 60 ],
					"midi[1]::notes[3]::toggle" : [ 1 ],
					"midi[1]::notes[2]::number" : [ 60 ],
					"midi[1]::notes[2]::toggle" : [ 1 ],
					"midi[1]::notes[1]::number" : [ 60 ],
					"midi[1]::notes[1]::toggle" : [ 1 ],
					"midi[1]::notes::number" : [ 60 ],
					"midi[1]::notes::toggle" : [ 1 ],
					"midi[1]::stepgroup::stepsel[15]::number" : [ 0 ],
					"midi[1]::stepgroup::stepsel[15]::toggle" : [ 0 ],
					"midi[1]::stepgroup::stepsel[14]::number" : [ 0 ],
					"midi[1]::stepgroup::stepsel[14]::toggle" : [ 0 ],
					"midi[1]::stepgroup::stepsel[13]::number" : [ 0 ],
					"midi[1]::stepgroup::stepsel[13]::toggle" : [ 0 ],
					"midi[1]::stepgroup::stepsel[12]::number" : [ 0 ],
					"midi[1]::stepgroup::stepsel[12]::toggle" : [ 0 ],
					"midi[1]::stepgroup::stepsel[11]::number" : [ 0 ],
					"midi[1]::stepgroup::stepsel[11]::toggle" : [ 0 ],
					"midi[1]::stepgroup::stepsel[10]::number" : [ 0 ],
					"midi[1]::stepgroup::stepsel[10]::toggle" : [ 0 ],
					"midi[1]::stepgroup::stepsel[9]::number" : [ 0 ],
					"midi[1]::stepgroup::stepsel[9]::toggle" : [ 0 ],
					"midi[1]::stepgroup::stepsel[8]::number" : [ 0 ],
					"midi[1]::stepgroup::stepsel[8]::toggle" : [ 0 ],
					"midi[1]::stepgroup::stepsel[7]::number" : [ 0 ],
					"midi[1]::stepgroup::stepsel[7]::toggle" : [ 0 ],
					"midi[1]::stepgroup::stepsel[6]::number" : [ 0 ],
					"midi[1]::stepgroup::stepsel[6]::toggle" : [ 0 ],
					"midi[1]::stepgroup::stepsel[5]::number" : [ 0 ],
					"midi[1]::stepgroup::stepsel[5]::toggle" : [ 0 ],
					"midi[1]::stepgroup::stepsel[4]::number" : [ 0 ],
					"midi[1]::stepgroup::stepsel[4]::toggle" : [ 0 ],
					"midi[1]::stepgroup::stepsel[3]::number" : [ 0 ],
					"midi[1]::stepgroup::stepsel[3]::toggle" : [ 0 ],
					"midi[1]::stepgroup::stepsel[2]::number" : [ 0 ],
					"midi[1]::stepgroup::stepsel[2]::toggle" : [ 0 ],
					"midi[1]::stepgroup::stepsel[1]::number" : [ 0 ],
					"midi[1]::stepgroup::stepsel[1]::toggle" : [ 0 ],
					"midi[1]::stepgroup::stepsel::number" : [ 0 ],
					"midi[1]::stepgroup::stepsel::toggle" : [ 0 ],
					"jr.noteouted[2]::number" : [ 1 ],
					"jr.noteouted[2]::number[1]" : [ 100 ],
					"jr.noteouted[2]::number[2]" : [ 500 ],
					"jr.noteouted[2]::number[3]" : [ 127 ],
					"jr.noteouted[2]::number[4]" : [ 0 ],
					"jr.noteouted[2]::number[5]" : [ 127 ],
					"jr.noteouted[2]::number[6]" : [ 0 ],
					"jr.noteouted[2]::number[7]" : [ 0 ],
					"jr.noteouted[2]::number[8]" : [ 10 ],
					"jr.noteouted[2]::number[9]" : [ 2000 ],
					"jr.noteouted[2]::toggle" : [ 0 ],
					"jr.noteouted[2]::toggle[1]" : [ 0 ],
					"jr.noteouted[2]::toggle[2]" : [ 1 ],
					"jr.noteouted[2]::toggle[3]" : [ 0 ],
					"grid::umenu" : [ 0 ],
					"midi::kslider" : [ -1 ],
					"midi::number" : [ 3 ],
					"midi::number[1]" : [ 16 ],
					"midi::umenu" : [ 5 ],
					"midi::notes[15]::number" : [ 60 ],
					"midi::notes[15]::toggle" : [ 1 ],
					"midi::notes[14]::number" : [ 60 ],
					"midi::notes[14]::toggle" : [ 1 ],
					"midi::notes[13]::number" : [ 60 ],
					"midi::notes[13]::toggle" : [ 1 ],
					"midi::notes[12]::number" : [ 60 ],
					"midi::notes[12]::toggle" : [ 1 ],
					"midi::notes[11]::number" : [ 60 ],
					"midi::notes[11]::toggle" : [ 1 ],
					"midi::notes[10]::number" : [ 60 ],
					"midi::notes[10]::toggle" : [ 1 ],
					"midi::notes[9]::number" : [ 60 ],
					"midi::notes[9]::toggle" : [ 1 ],
					"midi::notes[8]::number" : [ 60 ],
					"midi::notes[8]::toggle" : [ 1 ],
					"midi::notes[7]::number" : [ 60 ],
					"midi::notes[7]::toggle" : [ 1 ],
					"midi::notes[6]::number" : [ 60 ],
					"midi::notes[6]::toggle" : [ 1 ],
					"midi::notes[5]::number" : [ 60 ],
					"midi::notes[5]::toggle" : [ 1 ],
					"midi::notes[4]::number" : [ 60 ],
					"midi::notes[4]::toggle" : [ 1 ],
					"midi::notes[3]::number" : [ 60 ],
					"midi::notes[3]::toggle" : [ 1 ],
					"midi::notes[2]::number" : [ 60 ],
					"midi::notes[2]::toggle" : [ 1 ],
					"midi::notes[1]::number" : [ 60 ],
					"midi::notes[1]::toggle" : [ 1 ],
					"midi::notes::number" : [ 60 ],
					"midi::notes::toggle" : [ 1 ],
					"midi::stepgroup::stepsel[15]::number" : [ 0 ],
					"midi::stepgroup::stepsel[15]::toggle" : [ 0 ],
					"midi::stepgroup::stepsel[14]::number" : [ 0 ],
					"midi::stepgroup::stepsel[14]::toggle" : [ 0 ],
					"midi::stepgroup::stepsel[13]::number" : [ 0 ],
					"midi::stepgroup::stepsel[13]::toggle" : [ 0 ],
					"midi::stepgroup::stepsel[12]::number" : [ 0 ],
					"midi::stepgroup::stepsel[12]::toggle" : [ 0 ],
					"midi::stepgroup::stepsel[11]::number" : [ 0 ],
					"midi::stepgroup::stepsel[11]::toggle" : [ 0 ],
					"midi::stepgroup::stepsel[10]::number" : [ 0 ],
					"midi::stepgroup::stepsel[10]::toggle" : [ 0 ],
					"midi::stepgroup::stepsel[9]::number" : [ 0 ],
					"midi::stepgroup::stepsel[9]::toggle" : [ 0 ],
					"midi::stepgroup::stepsel[8]::number" : [ 0 ],
					"midi::stepgroup::stepsel[8]::toggle" : [ 0 ],
					"midi::stepgroup::stepsel[7]::number" : [ 0 ],
					"midi::stepgroup::stepsel[7]::toggle" : [ 0 ],
					"midi::stepgroup::stepsel[6]::number" : [ 0 ],
					"midi::stepgroup::stepsel[6]::toggle" : [ 0 ],
					"midi::stepgroup::stepsel[5]::number" : [ 0 ],
					"midi::stepgroup::stepsel[5]::toggle" : [ 0 ],
					"midi::stepgroup::stepsel[4]::number" : [ 0 ],
					"midi::stepgroup::stepsel[4]::toggle" : [ 0 ],
					"midi::stepgroup::stepsel[3]::number" : [ 0 ],
					"midi::stepgroup::stepsel[3]::toggle" : [ 0 ],
					"midi::stepgroup::stepsel[2]::number" : [ 0 ],
					"midi::stepgroup::stepsel[2]::toggle" : [ 0 ],
					"midi::stepgroup::stepsel[1]::number" : [ 0 ],
					"midi::stepgroup::stepsel[1]::toggle" : [ 0 ],
					"midi::stepgroup::stepsel::number" : [ 0 ],
					"midi::stepgroup::stepsel::toggle" : [ 0 ],
					"jr.noteouted[3]::number" : [ 1 ],
					"jr.noteouted[3]::number[1]" : [ 100 ],
					"jr.noteouted[3]::number[2]" : [ 500 ],
					"jr.noteouted[3]::number[3]" : [ 127 ],
					"jr.noteouted[3]::number[4]" : [ 0 ],
					"jr.noteouted[3]::number[5]" : [ 127 ],
					"jr.noteouted[3]::number[6]" : [ 0 ],
					"jr.noteouted[3]::number[7]" : [ 0 ],
					"jr.noteouted[3]::number[8]" : [ 10 ],
					"jr.noteouted[3]::number[9]" : [ 2000 ],
					"jr.noteouted[3]::toggle" : [ 0 ],
					"jr.noteouted[3]::toggle[1]" : [ 0 ],
					"jr.noteouted[3]::toggle[2]" : [ 1 ],
					"jr.noteouted[3]::toggle[3]" : [ 0 ]
				}

			}

		}

	}

}
